pyviewmaster/__init__.py
pyviewmaster/bulkreference.py
pyviewmaster/utils.py
pyviewmaster/viewmaster.py
pyviewmaster-0.1.2.dist-info/LICENSE
pyviewmaster-0.1.2.dist-info/METADATA
pyviewmaster-0.1.2.dist-info/WHEEL
pyviewmaster-0.1.2.dist-info/top_level.txt
pyviewmaster-0.1.2.dist-info/RECORD
