Metadata-Version: 2.1
Name: pyviewmaster
Version: 0.1.2
Summary: viewmastR uses machine learning implemented in Rust to perform automated cell type classification for single-cell genomic data.  Currently viewmastR is authored to work with scRNAseq data, but more features are coming.
Home-page: https://github.com/furlan-lab/pyviewmaster
Author: Scott Furlan
Author-email: scott.furlan@example.com
Classifier: Programming Language :: Python :: 3
Requires-Python: >=3.9
License-File: LICENSE
Requires-Dist: numpy
Requires-Dist: pandas
Requires-Dist: scanpy
Requires-Dist: scikit-learn
Requires-Dist: scipy
Requires-Dist: rds2py
Requires-Dist: biocframe
